pyproxmox_ve/__init__.py
pyproxmox_ve/api.py
pyproxmox_ve/auth.py
pyproxmox_ve/exceptions.py
pyproxmox_ve/models/base.py
pyproxmox_ve/models/enums.py
pyproxmox_ve/models/user.py
pyproxmox_ve/models/version.py
pyproxmox_ve/resources/__init__.py
pyproxmox_ve/resources/access/access.py
pyproxmox_ve/resources/access/users/users.py
pyproxmox_ve/resources/version.py
pyproxmox_ve-0.1.0a0.dist-info/LICENSE
pyproxmox_ve-0.1.0a0.dist-info/METADATA
pyproxmox_ve-0.1.0a0.dist-info/WHEEL
pyproxmox_ve-0.1.0a0.dist-info/RECORD
