Metadata-Version: 2.1
Name: pyproxmox-ve
Version: 0.1.0a0
Summary: Async wrapper (aiohttp) for Proxmox VE API
License: Apache Version 2.0
Author: Brandon Spendlove
Author-email: brandonspendlove@gmail.com
Requires-Python: >=3.10,<4.0
Classifier: License :: Other/Proprietary License
Classifier: Programming Language :: Python :: 3
Classifier: Programming Language :: Python :: 3.10
Classifier: Programming Language :: Python :: 3.11
Classifier: Programming Language :: Python :: 3.12
Requires-Dist: aiohttp (>=3.9.1,<4.0.0)
Requires-Dist: pydantic (>=2.5.3,<3.0.0)
